{"ExternalConditions": {"h_Left": 0.0, "h_Right": 0.0, "h_Front": 0.0, "h_Back": 0.0, "h_Bottom": 100000000.0, "h_Top": 0.0, "Ta_Left": 20.0, "Ta_Right": 20.0, "Ta_Front": 20.0, "Ta_Back": 20.0, "Ta_Bottom": 20.0, "Ta_Top": 20.0, "Tproc": 240.0}, "Params": {"Tsteps": [], "DeltaT": 1, "Tinit": 20.0}, "Features": [{"name": "die", "x": [-2500.0, 2500.0], "y": [-2500.0, 2500.0], "z": [2913.1250000000005, 3163.1250000000005], "dz": 2, "dy": 2, "dx": 2, "Q": 10.0, "Matl": "SiC"}, {"name": "solder2", "x": [-32968.75, 32968.75], "y": [-24218.75, 24218.75], "z": [2813.1250000000005, 2913.1250000000005], "dz": 2, "dy": 2, "dx": 2, "Q": 0.0, "Matl": "SAC405"}, {"name": "topmetal", "x": [-32968.75, 32968.75], "y": [-24218.75, 24218.75], "z": [2613.125, 2813.1250000000005], "dz": 2, "dy": 2, "dx": 2, "Q": 0.0, "Matl": "Cu"}, {"name": "ceramic", "x": [-32968.75, 32968.75], "y": [-24218.75, 24218.75], "z": [1978.125, 2613.125], "dz": 2, "dy": 2, "dx": 2, "Q": 0.0, "Matl": "AlN"}, {"name": "backmetal", "x": [-32968.75, 32968.75], "y": [-24218.75, 24218.75], "z": [1778.125, 1978.125], "dz": 2, "dy": 2, "dx": 2, "Q": 0.0, "Matl": "Cu"}, {"name": "solder1", "x": [-32968.75, 32968.75], "y": [-24218.75, 24218.75], "z": [1578.125, 1778.125], "dz": 2, "dy": 2, "dx": 2, "Q": 0.0, "Matl": "SAC405"}, {"name": "base", "x": [-32968.75, 32968.75], "y": [-24218.75, 24218.75], "z": [0.0, 1578.125], "dz": 2, "dy": 2, "dx": 2, "Q": 0.0, "Matl": "Al"}], "PottingMaterial": 0}