{"ExternalConditions": {"h_Left": 0.0, "h_Right": 0.0, "h_Front": 0.0, "h_Back": 0.0, "h_Bottom": 100000000.0, "h_Top": 0.0, "Ta_Left": 20.0, "Ta_Right": 20.0, "Ta_Front": 20.0, "Ta_Back": 20.0, "Ta_Bottom": 20.0, "Ta_Top": 20.0, "Tproc": 240.0}, "Params": {"Tsteps": [], "DeltaT": 1, "Tinit": 20.0}, "Features": [{"name": "die", "x": [-2500.0, 2500.0], "y": [-2500.0, 2500.0], "z": [6210.0, 6460.0], "dz": 2, "dy": 2, "dx": 2, "Q": 10.0, "Matl": "SiC"}, {"name": "solder2", "x": [-33750.0, 33750.0], "y": [-48750.0, 48750.0], "z": [6110.0, 6210.0], "dz": 2, "dy": 2, "dx": 2, "Q": 0.0, "Matl": "SAC405"}, {"name": "topmetal", "x": [-33750.0, 33750.0], "y": [-48750.0, 48750.0], "z": [5910.0, 6110.0], "dz": 2, "dy": 2, "dx": 2, "Q": 0.0, "Matl": "Cu"}, {"name": "ceramic", "x": [-33750.0, 33750.0], "y": [-48750.0, 48750.0], "z": [5275.0, 5910.0], "dz": 2, "dy": 2, "dx": 2, "Q": 0.0, "Matl": "AlN"}, {"name": "backmetal", "x": [-33750.0, 33750.0], "y": [-48750.0, 48750.0], "z": [5075.0, 5275.0], "dz": 2, "dy": 2, "dx": 2, "Q": 0.0, "Matl": "Cu"}, {"name": "solder1", "x": [-33750.0, 33750.0], "y": [-48750.0, 48750.0], "z": [4875.0, 5075.0], "dz": 2, "dy": 2, "dx": 2, "Q": 0.0, "Matl": "SAC405"}, {"name": "base", "x": [-33750.0, 33750.0], "y": [-48750.0, 48750.0], "z": [0.0, 4875.0], "dz": 2, "dy": 2, "dx": 2, "Q": 0.0, "Matl": "Al"}], "PottingMaterial": 0}