{"ExternalConditions": {"h_Left": 0.0, "h_Right": 0.0, "h_Front": 0.0, "h_Back": 0.0, "h_Bottom": 100000000.0, "h_Top": 0.0, "Ta_Left": 20.0, "Ta_Right": 20.0, "Ta_Front": 20.0, "Ta_Back": 20.0, "Ta_Bottom": 20.0, "Ta_Top": 20.0, "Tproc": 240.0}, "Params": {"Tsteps": [], "DeltaT": 1, "Tinit": 20.0}, "Features": [{"name": "die", "x": [-2500.0, 2500.0], "y": [-2500.0, 2500.0], "z": [4178.75, 4428.75], "dz": 2, "dy": 2, "dx": 2, "Q": 10.0, "Matl": "SiC"}, {"name": "solder2", "x": [-48437.5, 48437.5], "y": [-25312.5, 25312.5], "z": [4078.7500000000005, 4178.75], "dz": 2, "dy": 2, "dx": 2, "Q": 0.0, "Matl": "SAC405"}, {"name": "topmetal", "x": [-48437.5, 48437.5], "y": [-25312.5, 25312.5], "z": [3878.75, 4078.7500000000005], "dz": 2, "dy": 2, "dx": 2, "Q": 0.0, "Matl": "Cu"}, {"name": "ceramic", "x": [-48437.5, 48437.5], "y": [-25312.5, 25312.5], "z": [3243.7500000000005, 3878.75], "dz": 2, "dy": 2, "dx": 2, "Q": 0.0, "Matl": "AlN"}, {"name": "backmetal", "x": [-48437.5, 48437.5], "y": [-25312.5, 25312.5], "z": [3043.75, 3243.7500000000005], "dz": 2, "dy": 2, "dx": 2, "Q": 0.0, "Matl": "Cu"}, {"name": "solder1", "x": [-48437.5, 48437.5], "y": [-25312.5, 25312.5], "z": [2843.75, 3043.75], "dz": 2, "dy": 2, "dx": 2, "Q": 0.0, "Matl": "SAC405"}, {"name": "base", "x": [-48437.5, 48437.5], "y": [-25312.5, 25312.5], "z": [0.0, 2843.75], "dz": 2, "dy": 2, "dx": 2, "Q": 0.0, "Matl": "Al"}], "PottingMaterial": 0}